lvmtelemetry/__init__.py
lvmtelemetry/__main__.py
lvmtelemetry/actor/__init__.py
lvmtelemetry/actor/actor.py
lvmtelemetry/actor/commands/__init__.py
lvmtelemetry/actor/commands/status.py
lvmtelemetry/check_gude.py
lvmtelemetry/etc/lvmtelemetry.yml
lvmtelemetry/etc/schema.json
lvmtelemetry/gude_sensor.py
sdss_lvmtelemetry-0.2.2.dist-info/LICENSE.md
sdss_lvmtelemetry-0.2.2.dist-info/METADATA
sdss_lvmtelemetry-0.2.2.dist-info/WHEEL
sdss_lvmtelemetry-0.2.2.dist-info/entry_points.txt
sdss_lvmtelemetry-0.2.2.dist-info/RECORD
